serial_device/__init__.py
serial_device-0.4.post4.dist-info/DESCRIPTION.rst
serial_device-0.4.post4.dist-info/METADATA
serial_device-0.4.post4.dist-info/RECORD
serial_device-0.4.post4.dist-info/WHEEL
serial_device-0.4.post4.dist-info/metadata.json
serial_device-0.4.post4.dist-info/top_level.txt
