Metadata-Version: 2.0
Name: serial-device
Version: 0.4.post4
Summary: Simple, cross-platform interface for interacting with devices through a serial-port.
Home-page: https://github.com/wheeler-microfluidics/serial_device.git
Author: Ryan Fobel, Christian Fobel
Author-email: ryan@fobel.net, christian@fobel.net
License: GPLv2
Platform: UNKNOWN
Requires-Dist: pandas (>=0.18)
Requires-Dist: pyserial
